attendance_tracker_email/__init__.py
attendance_tracker_email/attendance.py
attendance_tracker_email/filetracker.py
attendance_tracker_email-0.1.5.dist-info/LICENSE
attendance_tracker_email-0.1.5.dist-info/METADATA
attendance_tracker_email-0.1.5.dist-info/WHEEL
attendance_tracker_email-0.1.5.dist-info/top_level.txt
attendance_tracker_email-0.1.5.dist-info/RECORD
