Metadata-Version: 2.1
Name: attendance_tracker_email
Version: 0.1.5
Summary: Attendance tracker package using emails
Author: morehwachege (Antony Muriithi Gakuru)
Author-email: <antony123muriithi@gmail.com>
Keywords: python,attendance,tracking,live stream,camera stream
Classifier: Development Status :: 1 - Planning
Classifier: Intended Audience :: Developers
Classifier: Programming Language :: Python :: 3
Classifier: Operating System :: Unix
Classifier: Operating System :: MacOS :: MacOS X
Classifier: Operating System :: Microsoft :: Windows
License-File: LICENSE
